crisprhawk/__init__.py
crisprhawk/__main__.py
crisprhawk/annotation.py
crisprhawk/bedfile.py
crisprhawk/bitset.py
crisprhawk/candidate_guides.py
crisprhawk/config_crispritz.py
crisprhawk/converter.py
crisprhawk/coordinate.py
crisprhawk/crisprhawk.py
crisprhawk/crisprhawk_argparse.py
crisprhawk/crisprhawk_error.py
crisprhawk/crisprhawk_version.py
crisprhawk/crisprme_data.py
crisprhawk/encoder.py
crisprhawk/exception_handlers.py
crisprhawk/graphical_reports.py
crisprhawk/guide.py
crisprhawk/haplotype.py
crisprhawk/haplotypes.py
crisprhawk/offtarget.py
crisprhawk/offtargets.py
crisprhawk/pam.py
crisprhawk/region.py
crisprhawk/region_constructor.py
crisprhawk/reports.py
crisprhawk/scoring.py
crisprhawk/search_guides.py
crisprhawk/search_offtargets.py
crisprhawk/sequence.py
crisprhawk/utils.py
crisprhawk/variant.py
crisprhawk/config/config.json
crisprhawk/scores/__init__.py
crisprhawk/scores/crisprhawk_scores.py
crisprhawk/scores/azimuth/FC_plus_RES_withPredictions.csv
crisprhawk/scores/azimuth/LICENSE.txt
crisprhawk/scores/azimuth/__init__.py
crisprhawk/scores/azimuth/cli_run_model.py
crisprhawk/scores/azimuth/cluster_job.py
crisprhawk/scores/azimuth/corrstats.py
crisprhawk/scores/azimuth/load_data.py
crisprhawk/scores/azimuth/local_multiprocessing.py
crisprhawk/scores/azimuth/metrics.py
crisprhawk/scores/azimuth/model_comparison.py
crisprhawk/scores/azimuth/model_comparison_py38.py
crisprhawk/scores/azimuth/predict.py
crisprhawk/scores/azimuth/saved_models.zip
crisprhawk/scores/azimuth/util.py
crisprhawk/scores/azimuth/data/FC_plus_RES_withPredictions.csv
crisprhawk/scores/azimuth/data/V1_data.xlsx
crisprhawk/scores/azimuth/data/V1_suppl_data.txt
crisprhawk/scores/azimuth/data/V2_data.xlsx
crisprhawk/scores/azimuth/features/__init__.py
crisprhawk/scores/azimuth/features/featurization.py
crisprhawk/scores/azimuth/features/microhomology.py
crisprhawk/scores/azimuth/models/DNN.py
crisprhawk/scores/azimuth/models/GP.py
crisprhawk/scores/azimuth/models/__init__.py
crisprhawk-0.1.1.dist-info/LICENSE
crisprhawk-0.1.1.dist-info/METADATA
crisprhawk-0.1.1.dist-info/WHEEL
crisprhawk-0.1.1.dist-info/entry_points.txt
crisprhawk-0.1.1.dist-info/top_level.txt
crisprhawk-0.1.1.dist-info/RECORD
