Metadata-Version: 2.1
Name: crisprhawk
Version: 0.1.1
Summary: CRISPR-HAWK: Haplotype and vAriant-aWare guide design toolKit
Home-page: https://github.com/pinellolab/CRISPR-HAWK
Author: Manuel Tognon
Author-email: Manuel Tognon <manu.tognon@gmail.com>
Maintainer-email: Manuel Tognon <manu.tognon@gmail.com>
License: AGPL-3
Project-URL: Homepage, https://github.com/pinellolab/CRISPR-HAWK
Project-URL: Documentation, https://github.com/pinellolab/CRISPR-HAWK
Project-URL: Repository, https://github.com/pinellolab/CRISPR-HAWK
Project-URL: Bug Tracker, https://github.com/pinellolab/CRISPR-HAWK/issues
Project-URL: Changelog, https://github.com/pinellolab/CRISPR-HAWK/blob/main/CHANGELOG.md
Keywords: CRISPR,guide RNA,haplotype,variant,bioinformatics
Classifier: Development Status :: 3 - Alpha
Classifier: Intended Audience :: Science/Research
Classifier: License :: OSI Approved :: GNU Affero General Public License v3
Classifier: Operating System :: OS Independent
Classifier: Programming Language :: Python :: 3
Classifier: Programming Language :: Python :: 3.8
Classifier: Topic :: Scientific/Engineering :: Bio-Informatics
Requires-Python: >=3.8
License-File: LICENSE
Requires-Dist: biopython==1.83
Requires-Dist: charset-normalizer==3.4.2
Requires-Dist: colorama==0.4.6
Requires-Dist: contourpy==1.1.1
Requires-Dist: cycler==0.12.1
Requires-Dist: et-xmlfile==2.0.0
Requires-Dist: exceptiongroup==1.2.2
Requires-Dist: filelock==3.16.1
Requires-Dist: fonttools==4.53.1
Requires-Dist: fsspec==2024.10.0
Requires-Dist: gmpy2==2.1.5
Requires-Dist: h5py==3.7.0
Requires-Dist: idna==3.10
Requires-Dist: iniconfig==2.0.0
Requires-Dist: Jinja2==3.1.4
Requires-Dist: joblib==1.4.2
Requires-Dist: kiwisolver==1.4.5
Requires-Dist: lightgbm==3.3.5
Requires-Dist: MarkupSafe==2.1.5
Requires-Dist: matplotlib==3.5.3
Requires-Dist: mpmath==1.3.0
Requires-Dist: munkres==1.1.4
Requires-Dist: networkx==3.1
Requires-Dist: numexpr==2.8.3
Requires-Dist: numpy==1.24.4
Requires-Dist: openpyxl==3.1.5
Requires-Dist: packaging==25.0
Requires-Dist: pandas==1.4.4
Requires-Dist: pillow==10.4.0
Requires-Dist: pluggy==1.5.0
Requires-Dist: pyarrow==17.0.0
Requires-Dist: pybedtools==0.10.0
Requires-Dist: pysam==0.22.1
Requires-Dist: pytest==8.3.4
Requires-Dist: requests==2.32.3
Requires-Dist: rs3==0.0.16
Requires-Dist: scikit-learn==1.1.1
Requires-Dist: scipy==1.9.1
Requires-Dist: seaborn==0.13.2
Requires-Dist: seqfold==0.7.18
Requires-Dist: sglearn==1.2.5
Requires-Dist: six==1.16.0
Requires-Dist: sympy==1.13.3
Requires-Dist: tables==3.7.0
Requires-Dist: threadpoolctl==3.5.0
Requires-Dist: torch==2.2.2
Requires-Dist: tornado==6.4.1
Requires-Dist: tqdm==4.67.1
Requires-Dist: typing-extensions==4.12.2
Requires-Dist: unicodedata2==15.1.0
Requires-Dist: urllib3==2.2.3
Requires-Dist: xlrd==2.0.1
Provides-Extra: dev
Requires-Dist: pytest; extra == "dev"
Requires-Dist: black; extra == "dev"
Requires-Dist: flake8; extra == "dev"
Requires-Dist: mypy; extra == "dev"
Provides-Extra: docs
Requires-Dist: sphinx; extra == "docs"
Requires-Dist: sphinx-rtd-theme; extra == "docs"
